prometheus_http_sdk/__init__.py
prometheus_http_sdk/prometheus_data_struct.py
prometheus_http_sdk/prometheus_exception.py
prometheus_http_sdk/prometheus_http.py
prometheus_http_sdk-0.0.4.dist-info/METADATA
prometheus_http_sdk-0.0.4.dist-info/WHEEL
prometheus_http_sdk-0.0.4.dist-info/top_level.txt
prometheus_http_sdk-0.0.4.dist-info/RECORD
