Metadata-Version: 2.1
Name: prometheus-http-sdk
Version: 0.0.4
Summary: prometheus http sdk
Home-page: https://github.com/RedheatWei/prometheus_http_sdk_py
Author: Redheat
Author-email: qjyyn@qq.com
License: Apache License 2.0
Download-URL: https://github.com/RedheatWei/prometheus_http_sdk_py
Platform: UNKNOWN
Classifier: License :: OSI Approved :: Apache Software License
Classifier: Natural Language :: English
Classifier: Operating System :: OS Independent
Classifier: Programming Language :: Python
Classifier: Programming Language :: Python :: 3.4
Classifier: Programming Language :: Python :: 3.5
Classifier: Programming Language :: Python :: 3.6
Classifier: Programming Language :: Python :: 3.7
Classifier: Topic :: Software Development :: Libraries :: Python Modules
Requires-Dist: requests
